{
  "name": "Callie Lee",
  "age": 34,
  "address": {
    "street": "Ezej Pike",
    "city": "Docezeko",
    "state": "ID",
    "zip": "96681"
  },
  "contact": {
    "phone": "(888) 867-2328",
    "servicePhone": "800626549"
  },
  "birthday": "1984-06-29T12:19:02.309Z",
  "ip": "78.57.133.240",
  "foo": "bar",
  "profile": {
    "about": "Ujeehuef tativiviw cefsuvi corzusmir deholhi nojag coto hupha pun du poz viotuvu uj izo goga ri kahij. Lavanuse daco se cev popihuaf utfejazo wibfeol kedjaca si izdejzel fokagol nofwet ne. Zedfamvam punes nahjohor ho du dic voif ateonvog heh bulve koub bizfiki. Fiwdu vulho to uwokidos tapin fu gujjuswo lerewwe tica ze ve re as nojeto ewasmat zuve bebaga febof. Setesu juosjo feja tolopge ceflohu daud vev cazwi sa didub vozir fiwpegbez nesto irfo abge joacijer ef bu. Wan ke zankij tefuve hav lub ihli lutap sonu jo sa ko kelirit ki hizsi lap huk japsohi. Ivfa winanke zebum wihimbe enkul ipopicru ri sodvib powwiw no ervazre lum aknepu ikadek risi ekeuwjo fuwka in.",
    "bio": "Paivo zihsegji avajazu ses zacdetnov itavabtoj emu mo lohtu lonij cunownu pidadu. Zorepwos iku nucrisji guwsar fa kooco vilicur izadeg lopuig buwsap dazjam po ni. Nepohe ju sanpehmis ja fe zicgicpup otawednav radutbe burpeut mi jecewuw li in. Ul puvjaz luv ac va viv unku zewomgam tehka debmec inama couz. Hif dudvadu atina wev kig bikvado ideifi sourara wil atloup se aclog ziemu zojmok bahmajwu totabit se."
  },
  "apiKey": "3276bbe0ffb181874abe72cf9bad90be37892be84a1e594da481cf6d8f405904",
  "currency": {
    "code": "VEF",
    "name": "Venezuela Bolivar"
  }
}